{
  "Sex Pistols": "https://pt.wikipedia.org/wiki/Sex_Pistols",
  "The Clash": "https://pt.wikipedia.org/wiki/The_Clash",
  "Ramones": "https://pt.wikipedia.org/wiki/Ramones",
  "Dead Kennedys": "https://pt.wikipedia.org/wiki/Dead_Kennedys",
  "Bad Brains": "https://pt.wikipedia.org/wiki/Bad_Brains",
  "proto-punk": "https://pt.wikipedia.org/wiki/Protopunk",
  "The Stooges": "https://pt.wikipedia.org/wiki/The_Stooges",
  "Iggy Pop": "https://pt.wikipedia.org/wiki/Iggy_Pop",
  "MC5": "https://pt.wikipedia.org/wiki/MC5",
  "Velvet Underground": "https://pt.wikipedia.org/wiki/The_Velvet_Underground",
  "New York Dolls": "https://pt.wikipedia.org/wiki/New_York_Dolls",
  "CBGB": "https://pt.wikipedia.org/wiki/CBGB",
  "Television": "https://en.wikipedia.org/wiki/Television_(band)",
  "Patti Smith": "https://pt.wikipedia.org/wiki/Patti_Smith",
  "Richard Hell": "https://pt.wikipedia.org/wiki/Richard_Hell",
  "Richard Hell and the Voidoids": "https://pt.wikipedia.org/wiki/Richard_Hell_and_the_Voidoids",
  "The Damned": "https://pt.wikipedia.org/wiki/The_Damned_(band)",
  "Buzzcocks": "https://pt.wikipedia.org/wiki/Buzzcocks",
  "Restos de Nada": "https://pt.wikipedia.org/wiki/Restos_de_Nada",
  "fanzines": "https://pt.wikipedia.org/wiki/Fanzine", 
  "do-it-yourself": "https://pt.wikipedia.org/wiki/Do_it_yourself_(punk)", 
  "Vivienne Westwood": "https://pt.wikipedia.org/wiki/Vivienne_Westwood",
  "Malcolm McLaren": "https://pt.wikipedia.org/wiki/Malcolm_McLaren",
  "hardcore punk": "https://pt.wikipedia.org/wiki/Hardcore_punk",
  "anarcho-punk": "https://pt.wikipedia.org/wiki/Anarcho-punk",
  "street punk": "https://pt.wikipedia.org/wiki/Street_punk",
  "Black Flag": "https://en.wikipedia.org/wiki/Black_Flag_(band)",
  "Circle Jerks": "https://pt.wikipedia.org/wiki/Circle_Jerks",
  "Dischord Records": "https://pt.wikipedia.org/wiki/Dischord_Records",
  "Ian MacKaye": "https://pt.wikipedia.org/wiki/Ian_MacKaye",
  "Jeff Nelson": "https://en.wikipedia.org/wiki/Jeff_Nelson_(musician)",
  "Minor Threat": "https://pt.wikipedia.org/wiki/Minor_Threat",
  "straight edge": "https://pt.wikipedia.org/wiki/Straight_edge",
  "Crass": "https://pt.wikipedia.org/wiki/Crass",
  "GBH": "https://en.wikipedia.org/wiki/GBH_(band)",
  "The Exploited": "https://en.wikipedia.org/wiki/The_Exploited ",
  "UK82": "https://en.wikipedia.org/wiki/Street_punk#UK_82", 
  "Aborto Elétrico":"",
  "Inocentes": "https://pt.wikipedia.org/wiki/Inocentes_(banda)",
  "Cólera": "https://pt.wikipedia.org/wiki/C%C3%B3lera_(banda)",
  "Olho Seco": "https://pt.wikipedia.org/wiki/Olho_Seco",
  "Ratos de Porão": "https://pt.wikipedia.org/wiki/Ratos_de_Por%C3%A3o",
  "O Começo do Fim do Mundo": "https://pt.wikipedia.org/wiki/O_Come%C3%A7o_do_Fim_do_Mundo",
  "pop punk": "https://pt.wikipedia.org/wiki/Pop_punk",
  "Green Day": "https://pt.wikipedia.org/wiki/Green_Day",
  "The Offspring": "https://pt.wikipedia.org/wiki/The_Offspring",
  "Reprise Records": "https://pt.wikipedia.org/wiki/Reprise_Records",
  "Rancid": "https://en.wikipedia.org/wiki/Rancid_(band)",
  "ska": "https://pt.wikipedia.org/wiki/Ska",
  "NOFX": "https://pt.wikipedia.org/wiki/NOFX",
  "Bad Religion": "https://pt.wikipedia.org/wiki/Bad_Religion",
  "Warped Tour": "https://pt.wikipedia.org/wiki/Warped_Tour",
  "Blink-182": "https://pt.wikipedia.org/wiki/Blink-182",
  "Millencolin": "https://pt.wikipedia.org/wiki/Millencolin",
  "punk melódico": "https://pt.wikipedia.org/wiki/Hardcore_mel%C3%B3dico", 
  "The Wildhearts": "https://en.wikipedia.org/wiki/The_Wildhearts",
  "Snuff": "https://en.wikipedia.org/wiki/Snuff_(British_band)  ",
  "indie rock": "https://pt.wikipedia.org/wiki/Indie_rock",
  "britpop": "https://pt.wikipedia.org/wiki/Britpop",
  "Dead Fish": "https://pt.wikipedia.org/wiki/Dead_Fish",
  "hardcore melódico": "https://pt.wikipedia.org/wiki/Hardcore_mel%C3%B3dico", 
  "Vans": "https://pt.wikipedia.org/wiki/Vans",
  "Converse": "https://pt.wikipedia.org/wiki/Converse_(empresa)",
  "Fun People": "https://es.wikipedia.org/wiki/Fun_People",
  "2 minutos": "https://es.wikipedia.org/wiki/2_Minutos", 
  "emo": "https://pt.wikipedia.org/wiki/Emo",
  "metal alternativo": "https://pt.wikipedia.org/wiki/Alternative_metal",
  "Sum 41": "https://pt.wikipedia.org/wiki/Sum_41",
  "Good Charlotte": "https://pt.wikipedia.org/wiki/Good_Charlotte",
  "Simple Plan": "https://pt.wikipedia.org/wiki/Simple_Plan",
  "MTV": "https://pt.wikipedia.org/wiki/MTV",
  "My Chemical Romance": "https://pt.wikipedia.org/wiki/My_Chemical_Romance",
  "pós-hardcore": "https://pt.wikipedia.org/wiki/Post-hardcore",
  "My Space": "https://pt.wikipedia.org/wiki/MySpace",
  "The Story So Far": "https://en.wikipedia.org/wiki/The_Story_So_Far_(band)",
  "Neck Deep": "https://pt.wikipedia.org/wiki/Neck_Deep",
  "State Champs": "https://pt.wikipedia.org/wiki/State_Champs",
  "PUP": "https://en.wikipedia.org/wiki/PUP_(band)",
  "Against Me!": "https://pt.wikipedia.org/wiki/Against_Me!",
  "pós-punk contemporâneo": "https://pt.wikipedia.org/wiki/P%C3%B3s-punk", 
  "IDLES": "https://pt.wikipedia.org/wiki/Idles_(banda)",
  "Fontaines D.C": "https://en.wikipedia.org/wiki/Fontaines_D.C.",
  "Bandcamp": "https://en.wikipedia.org/wiki/Bandcamp",
  "YouTube": "https://en.wikipedia.org/wiki/YouTube",
  "streetwear": "https://en.wikipedia.org/wiki/Streetwear", 
  "Amyl and The Sniffers": "https://pt.wikipedia.org/wiki/Amyl_and_the_Sniffers",
  "Turnstile": "https://en.wikipedia.org/wiki/Turnstile_(band)",
  "Meet Me @ The Altar": "https://en.wikipedia.org/wiki/Meet_Me_at_the_Altar",		
  "Pinkshift": "https://en.wikipedia.org/wiki/Pinkshift"	
}
